{"cameraMode":{"drawMode":0,"name":"Shaded","section":"Shading Mode"},"sceneLighting":true,"audioPlay":false,"sceneViewState":{"m_AlwaysRefresh":false,"showFog":true,"showSkybox":true,"showFlares":true,"showImageEffects":true,"showParticleSystems":true,"showVisualEffectGraphs":true,"m_FxEnabled":true},"in2DMode":false,"pivot":{"x":2.5607566833496095,"y":-4.249574661254883,"z":-11.233768463134766},"rotation":{"x":-0.05493888258934021,"y":0.9447133541107178,"z":-0.21504171192646027,"w":-0.24143008887767793},"size":11.411661148071289,"orthographic":false}